README.rst
setup.py
rdalal/__init__.py
rdalal/cmdline.py
rdalal.egg-info/PKG-INFO
rdalal.egg-info/SOURCES.txt
rdalal.egg-info/dependency_links.txt
rdalal.egg-info/entry_points.txt
rdalal.egg-info/top_level.txt
rdalal.egg-info/zip-safe